[
  {
    "id": "med_medicine_data_1p~500p_13_벳클로_비듬방지_피부보호삼푸",
    "text": "문서유형: 동물용의약품 | 제품명: 벳클로 비듬방지 피부보호삼푸 | 제조업체: (주)크린피스 | 품목정보: 동물용의약외품-제조-095-112 | 키워드: 벳클로 비듬방지 피부보호삼푸, Vat skin antidandruff shampoo, (주)크린피스, 애완견의 비듬과 각질을 감소시켜 주는 삼푸로서 모발\n보호와 세정작용을 한다.\\n\\n제품명: 벳클로 비듬방지 피부보호삼푸\\n영문명: Vat skin antidandruff shampoo\\n제조업체: (주)크린피스\\n허가일: 2010-04-14\\n성상: 적색의 점도있는 액상\\n\\n효능효과: 애완견의 비듬과 각질을 감소시켜 주는 삼푸로서 모발\n보호와 세정작용을 한다.\\n\\n용법용량:\\n가. 적당한 온수로 애견의 피부를 충분히 적셔 주십시\n    오\n나. 충분한 거품과 함께 애견의 전신을 약4～5분 간 \n    맛사지 하듯 삼푸하십시오\n다. 삼푸후 충분히 헹궈 삼푸기를 완전히 제거해 주십\n    시오\n라. 털이 완전히 마를때까지 충분히 드라이 해 주십시\n    오\n마. 증상이 없어 질 때까지 1주 1-2회 간격으로 사용\n    하십시오.\\n\\n주의사항: 가. 수의사의 지시에 따라 사용할 것.\n나. 사용상 붉은 반점, 부어오름, 가려움증 등의 증상\n    이 나타날 경우 사용을 중지하고 수의사와 상담\n    할 것.\n다. 상처, 습진, 피부염 등의 이상이 있을시 사용하\n    지 말 것.\n라. 눈에 들어갔을 경우에는 즉시 씻을 것.\n마. 용도외에 사용하지 말 것.\n바. 어린이 손에 닿지 않는 곳에 보관 할 것.\n사. 직사광선이 닿는 곳 이나 고온 내지 저온의 장소\n    에 보관하지 말 것.",
    "metadata": {
      "source_file": "medicine_data_1p~500p.csv",
      "source_type": "csv_medication",
      "batch_number": 13,
      "company": "(주)크린피스",
      "approval_date": "2010-04-14",
      "product_type": "동물용의약외품-제조-095-112",
      "approval_status": "정상",
      "manufacturing_type": "제조",
      "product_name": "벳클로 비듬방지 피부보호삼푸",
      "keywords": [
        "벳클로 비듬방지 피부보호삼푸",
        "Vat skin antidandruff shampoo",
        "(주)크린피스",
        "애완견의 비듬과 각질을 감소시켜 주는 삼푸로서 모발\n보호와 세정작용을 한다."
      ],
      "content_type": "medication_info"
    }
  },
  {
    "id": "med_medicine_data_1p~500p_13_웅자_향이_좋은_탈취제(아쿠아후레쉬향)",
    "text": "문서유형: 동물용의약품 | 제품명: 웅자 향이 좋은 탈취제(아쿠아후레쉬향) | 제조업체: (주)크린피스 | 품목정보: 동물용의약외품-제조-095-181 | 키워드: 웅자 향이 좋은 탈취제(아쿠아후레쉬향), Wongja good smell deodorant(Aqua fresh perfume), (주)크린피스, 애완동물에 의해 발생되는 악취를 제거하고 환경을 청결하고 신선하게 해줍니다.\\n\\n제품명: 웅자 향이 좋은 탈취제(아쿠아후레쉬향)\\n영문명: Wongja good smell deodorant(Aqua fresh perfume)\\n제조업체: (주)크린피스\\n허가일: 2016-06-20\\n성상: 무색내지 연미색 액상\\n\\n효능효과: 애완동물에 의해 발생되는 악취를 제거하고 환경을 청결하고 신선하게 해줍니다.\\n\\n용법용량:\\n가. 애완동물의 몸이나 주변에서 악취가 날 때 직접 3∼4회 분무해 주십시오.\n나. 애완용품 주거 장소 또는 기타악취가 나거나 필요한 곳에 분무해 주십시오.\\n\\n주의사항: 가. 사람이나 동물의 눈에 들어가지 않게 조심해 분무할 것.\n나. 눈에 들어갔을 때에는 즉시 씻을 것\n다. 어린이의 손에 닿지 않는 곳에 보관할 것.\n라. 고온내지 저온의 장소 및 일광이 닿는 곳에는 보관하지 말 것.\n마. 사용후 마개를 닫아 주십시오",
    "metadata": {
      "source_file": "medicine_data_1p~500p.csv",
      "source_type": "csv_medication",
      "batch_number": 13,
      "company": "(주)크린피스",
      "approval_date": "2016-06-20",
      "product_type": "동물용의약외품-제조-095-181",
      "approval_status": "정상",
      "manufacturing_type": "제조",
      "product_name": "웅자 향이 좋은 탈취제(아쿠아후레쉬향)",
      "keywords": [
        "웅자 향이 좋은 탈취제(아쿠아후레쉬향)",
        "Wongja good smell deodorant(Aqua fresh perfume)",
        "(주)크린피스",
        "애완동물에 의해 발생되는 악취를 제거하고 환경을 청결하고 신선하게 해줍니다."
      ],
      "content_type": "medication_info"
    }
  },
  {
    "id": "med_medicine_data_1p~500p_13_웅자_향이좋은_탈취제(베이비파우더향)",
    "text": "문서유형: 동물용의약품 | 제품명: 웅자 향이좋은 탈취제(베이비파우더향) | 제조업체: (주)크린피스 | 품목정보: 동물용의약외품-제조-095-182 | 키워드: 웅자 향이좋은 탈취제(베이비파우더향), Woongja good smell deodorant(Baby powder perfume), (주)크린피스, 애완동물에 의해 발생되는 악취를 제거하고 환경을 청결하고 신선하게 해줍니다.\\n\\n제품명: 웅자 향이좋은 탈취제(베이비파우더향)\\n영문명: Woongja good smell deodorant(Baby powder perfume)\\n제조업체: (주)크린피스\\n허가일: 2016-06-20\\n성상: 연미색내지 미황색 액상\\n\\n효능효과: 애완동물에 의해 발생되는 악취를 제거하고 환경을 청결하고 신선하게 해줍니다.\\n\\n용법용량:\\n가. 애완동물의 몸이나 주변에서 악취가 날 때 직접 3∼4회 분무해 주십시오.\n나. 애완용품 주거 장소 또는 기타악취가 나거나 필요한 곳에 분무해 주십시오.\\n\\n주의사항: 가. 사람이나 동물의 눈에 들어가지 않게 조심해 분무할 것.\n나. 눈에 들어갔을 때에는 즉시 씻을 것\n다. 어린이의 손에 닿지 않는 곳에 보관할 것.\n라. 고온내지 저온의 장소 및 일광이 닿는 곳에는 보관하지 말 것.\n마. 사용후 마개를 닫아 주십시오",
    "metadata": {
      "source_file": "medicine_data_1p~500p.csv",
      "source_type": "csv_medication",
      "batch_number": 13,
      "company": "(주)크린피스",
      "approval_date": "2016-06-20",
      "product_type": "동물용의약외품-제조-095-182",
      "approval_status": "정상",
      "manufacturing_type": "제조",
      "product_name": "웅자 향이좋은 탈취제(베이비파우더향)",
      "keywords": [
        "웅자 향이좋은 탈취제(베이비파우더향)",
        "Woongja good smell deodorant(Baby powder perfume)",
        "(주)크린피스",
        "애완동물에 의해 발생되는 악취를 제거하고 환경을 청결하고 신선하게 해줍니다."
      ],
      "content_type": "medication_info"
    }
  },
  {
    "id": "med_medicine_data_1p~500p_13_웅자_덴탈센스_바르는_치약",
    "text": "문서유형: 동물용의약품 | 제품명: 웅자 덴탈센스 바르는 치약 | 제조업체: (주)크린피스 | 품목정보: 동물용의약외품-제조-095-183 | 키워드: 웅자 덴탈센스 바르는 치약, Woongja Dental sense toothpaste, (주)크린피스, 애견의 구강내 치아 보호 및 구강청량, 냄새제거\\n\\n제품명: 웅자 덴탈센스 바르는 치약\\n영문명: Woongja Dental sense toothpaste\\n제조업체: (주)크린피스\\n허가일: 2016-06-22\\n성상: 연미색의 점성액상\\n\\n효능효과: 애견의 구강내 치아 보호 및 구강청량, 냄새제거\\n\\n용법용량:\\n애완 동물의 입술을 들어올려 잇몸과 치아 사이에 발라줍니다.\\n\\n주의사항: 가. 애완동물용이므로 사람에게는 사용하지 말것.\n나. 구강, 치아에 질병이 있는 개와 고양이에게는 수의사와 상담 후 사용할 것.\n다. 사용 후 마개를 닫아둘 것.\n라. 유, 소아의 손에 닿지 않는 곳에 보관할 것.\n마. 고온 내지 저온의 장소 및 일광이 닿는 곳에는 보관하지 말것.",
    "metadata": {
      "source_file": "medicine_data_1p~500p.csv",
      "source_type": "csv_medication",
      "batch_number": 13,
      "company": "(주)크린피스",
      "approval_date": "2016-06-22",
      "product_type": "동물용의약외품-제조-095-183",
      "approval_status": "정상",
      "manufacturing_type": "제조",
      "product_name": "웅자 덴탈센스 바르는 치약",
      "keywords": [
        "웅자 덴탈센스 바르는 치약",
        "Woongja Dental sense toothpaste",
        "(주)크린피스",
        "애견의 구강내 치아 보호 및 구강청량",
        "냄새제거"
      ],
      "content_type": "medication_info"
    }
  },
  {
    "id": "med_medicine_data_1p~500p_13_까만코블랙",
    "text": "문서유형: 동물용의약품 | 제품명: 까만코블랙 | 제조업체: (주)크린피스 | 품목정보: 동물용의약외품-제조-095-184 | 키워드: 까만코블랙, KKAMANCO BLACK, (주)크린피스, 가. 애견의 피모나 피부의 착색\\n\\n제품명: 까만코블랙\\n영문명: KKAMANCO BLACK\\n제조업체: (주)크린피스\\n허가일: 2016-08-25\\n성상: 검정색의 점성액상\\n\\n효능효과: 가. 애견의 피모나 피부의 착색\\n\\n용법용량:\\n애견의 피모나 피부에 적당량을 문질러 착색시킨다.\\n\\n주의사항: 가. 애완동물용이므로 사람에게는 사용하지 말것.\n나. 피부에 질병이 있는 개와 고양이에게는 수의사와 상담 후 사용할 것.\n다. 사용 후 마개를 닫아둘 것.\n라. 유, 소아의 손에 닿지 않는 곳에 보관할 것.\n마. 고온 내지 저온의 장소 및 일광이 닿는 곳에는 보관하지 말것.",
    "metadata": {
      "source_file": "medicine_data_1p~500p.csv",
      "source_type": "csv_medication",
      "batch_number": 13,
      "company": "(주)크린피스",
      "approval_date": "2016-08-25",
      "product_type": "동물용의약외품-제조-095-184",
      "approval_status": "정상",
      "manufacturing_type": "제조",
      "product_name": "까만코블랙",
      "keywords": [
        "까만코블랙",
        "KKAMANCO BLACK",
        "(주)크린피스",
        "가. 애견의 피모나 피부의 착색"
      ],
      "content_type": "medication_info"
    }
  },
  {
    "id": "med_medicine_data_1p~500p_13_까만코브라운",
    "text": "문서유형: 동물용의약품 | 제품명: 까만코브라운 | 제조업체: (주)크린피스 | 품목정보: 동물용의약외품-제조-095-185 | 키워드: 까만코브라운, KKAMANCO BROWN, (주)크린피스, 가. 애견의 피모나 피부의 착색\\n\\n제품명: 까만코브라운\\n영문명: KKAMANCO BROWN\\n제조업체: (주)크린피스\\n허가일: 2016-08-25\\n성상: 갈색의 점성액상\\n\\n효능효과: 가. 애견의 피모나 피부의 착색\\n\\n용법용량:\\n애견의 피모나 피부에 적당량을 문질러 착색시킨다.\\n\\n주의사항: 가. 애완동물용이므로 사람에게는 사용하지 말것.\n나. 피부에 질병이 있는 개와 고양이에게는 수의사와 상담 후 사용할 것.\n다. 사용 후 마개를 닫아둘 것.\n라. 유, 소아의 손에 닿지 않는 곳에 보관할 것.\n마. 고온 내지 저온의 장소 및 일광이 닿는 곳에는 보관하지 말것.",
    "metadata": {
      "source_file": "medicine_data_1p~500p.csv",
      "source_type": "csv_medication",
      "batch_number": 13,
      "company": "(주)크린피스",
      "approval_date": "2016-08-25",
      "product_type": "동물용의약외품-제조-095-185",
      "approval_status": "정상",
      "manufacturing_type": "제조",
      "product_name": "까만코브라운",
      "keywords": [
        "까만코브라운",
        "KKAMANCO BROWN",
        "(주)크린피스",
        "가. 애견의 피모나 피부의 착색"
      ],
      "content_type": "medication_info"
    }
  },
  {
    "id": "med_medicine_data_1p~500p_13_캐니바쓰오트밀삼푸",
    "text": "문서유형: 동물용의약품 | 제품명: 캐니바쓰오트밀삼푸 | 제조업체: (주)크린피스 | 품목정보: 동물용의약외품-제조-095-186 | 키워드: 캐니바쓰오트밀삼푸, Canibath Oatmeal shampoo, (주)크린피스, 가. 애완견과 고양이의 애완견의 비듬과 각질을 감소시켜 주는 삼푸로서 모발\n    보호와 세정작용 및 탈모방지\\n\\n제품명: 캐니바쓰오트밀삼푸\\n영문명: Canibath Oatmeal shampoo\\n제조업체: (주)크린피스\\n허가일: 2016-10-13\\n성상: 미색의 점도있는 액상.\\n\\n효능효과: 가. 애완견과 고양이의 애완견의 비듬과 각질을 감소시켜 주는 삼푸로서 모발\n    보호와 세정작용 및 탈모방지\\n\\n용법용량:\\n가. 적당한 온수로 애견의 피부를 충분히 적셔 주십시오\n나. 충분한 거품과 함께 애견의 전신을 맛사지 하듯 삼푸하십시오\n다. 삼푸후 충분히 헹궈 삼푸기를 완전히 제거해 주십시오\n라. 털이 완전히 마를때까지 충분히 드라이 해 주십시오\\n\\n주의사항: 가. 용도이외에는 사용하지 마십시오\n나. 눈이나 귀에 들어가지 않도록 하시고 만약 들어 갔을 경우 흐르는 물로 \n    닦아 주십시오\n다. 직사광선이 닿는 곳 이나 고온 내지 저온의 장소에 보관하지 마십시오.\n라. 어린이 손에 닿지 않는 곳에 보관하십시오.",
    "metadata": {
      "source_file": "medicine_data_1p~500p.csv",
      "source_type": "csv_medication",
      "batch_number": 13,
      "company": "(주)크린피스",
      "approval_date": "2016-10-13",
      "product_type": "동물용의약외품-제조-095-186",
      "approval_status": "정상",
      "manufacturing_type": "제조",
      "product_name": "캐니바쓰오트밀삼푸",
      "keywords": [
        "캐니바쓰오트밀삼푸",
        "Canibath Oatmeal shampoo",
        "(주)크린피스",
        "가. 애완견과 고양이의 애완견의 비듬과 각질을 감소시켜 주는 삼푸로서 모발\n    보호와 세정작용 및 탈모방지"
      ],
      "content_type": "medication_info"
    }
  },
  {
    "id": "med_medicine_data_1p~500p_13_엔큐_항균_탈취제",
    "text": "문서유형: 동물용의약품 | 제품명: 엔큐 항균 탈취제 | 제조업체: (주)크린피스 | 품목정보: 동물용의약외품-제조-095-113 | 키워드: 엔큐 항균 탈취제, NQ deodorant, (주)크린피스, 애완동물에 의해 발생되는 악취를 제거하고 항균작용\n성분을 부여하여 환경을 청결하고 신선하게 해줍니다.\\n\\n제품명: 엔큐 항균 탈취제\\n영문명: NQ deodorant\\n제조업체: (주)크린피스\\n허가일: 2010-08-11\\n성상: 투명한 연청색 액상\\n\\n효능효과: 애완동물에 의해 발생되는 악취를 제거하고 항균작용\n성분을 부여하여 환경을 청결하고 신선하게 해줍니다.\\n\\n용법용량:\\n가. 애완동물의 몸이나 주변에서 악취가 날 때 직접  \n    3~4회 분무해 주십시오.\n나. 애완용품 주거 장소 또는 기타악취가 나거나 항균\n    작용이 필요한 곳에 분무해 주십시오.\\n\\n주의사항: 가. 사람이나 동물의 눈에 들어가지 않게 조심해 분무\n    할 것.\n나. 눈에 들어갔을 때에는 즉시 씻을 것\n다. 어린이의 손에 닿지 않는 곳에 보관할 것.\n라. 고온내지 저온의 장소 및 일광이 닿는 곳에는 보\n    관하지 말 것.\n마. 사용후 마개를 닫아 주십시오",
    "metadata": {
      "source_file": "medicine_data_1p~500p.csv",
      "source_type": "csv_medication",
      "batch_number": 13,
      "company": "(주)크린피스",
      "approval_date": "2010-08-11",
      "product_type": "동물용의약외품-제조-095-113",
      "approval_status": "정상",
      "manufacturing_type": "제조",
      "product_name": "엔큐 항균 탈취제",
      "keywords": [
        "엔큐 항균 탈취제",
        "NQ deodorant",
        "(주)크린피스",
        "애완동물에 의해 발생되는 악취를 제거하고 항균작용\n성분을 부여하여 환경을 청결하고 신선하게 해줍니다."
      ],
      "content_type": "medication_info"
    }
  },
  {
    "id": "med_medicine_data_1p~500p_13_비타민캡슐_삼푸린스(전견용)",
    "text": "문서유형: 동물용의약품 | 제품명: 비타민캡슐 삼푸린스(전견용) | 제조업체: (주)크린피스 | 품목정보: 동물용의약외품-제조-095-114 | 키워드: 비타민캡슐 삼푸린스(전견용), Vitamine capsule normal shampoo rinse), (주)크린피스, 애완견과 고양이의 모발보호와 세정작용\\n\\n제품명: 비타민캡슐 삼푸린스(전견용)\\n영문명: Vitamine capsule normal shampoo rinse)\\n제조업체: (주)크린피스\\n허가일: 2011-05-20\\n성상: 알갱이가 있는 연노란색의 점도있는 액상.\\n\\n효능효과: 애완견과 고양이의 모발보호와 세정작용\\n\\n용법용량:\\n가. 적당한 온수로 애견의 피부를 충분히 적셔 주십시\n    오\n나. 충분한 거품과 함께 애견의 전신을 맛사지 하듯 \n    삼푸하십시오\n다. 삼푸후 충분히 헹궈 삼푸기를 완전히 제거해 주십\n    시오\n라. 털이 완전히 마를때까지 충분히 드라이 해 주십시\n    오\\n\\n주의사항: 가. 용도이외에는 사용하지 마십시오\n나. 눈이나 귀에 들어가지 않도록 하시고 만약 들어 \n    갔을 경우 흐르는 물로 닦아 주십시오\n다. 직사광선이 닿는 곳 이나 고온 내지 저온의 장소\n    에 보관하지 마십시오.\n라. 어린이 손에 닿지 않는 곳에 보관하십시오.",
    "metadata": {
      "source_file": "medicine_data_1p~500p.csv",
      "source_type": "csv_medication",
      "batch_number": 13,
      "company": "(주)크린피스",
      "approval_date": "2011-05-20",
      "product_type": "동물용의약외품-제조-095-114",
      "approval_status": "정상",
      "manufacturing_type": "제조",
      "product_name": "비타민캡슐 삼푸린스(전견용)",
      "keywords": [
        "비타민캡슐 삼푸린스(전견용)",
        "Vitamine capsule normal shampoo rinse)",
        "(주)크린피스",
        "애완견과 고양이의 모발보호와 세정작용"
      ],
      "content_type": "medication_info"
    }
  },
  {
    "id": "med_medicine_data_1p~500p_13_비타민캡슐_삼푸린스(자견용)",
    "text": "문서유형: 동물용의약품 | 제품명: 비타민캡슐 삼푸린스(자견용) | 제조업체: (주)크린피스 | 품목정보: 동물용의약외품-제조-095-115 | 키워드: 비타민캡슐 삼푸린스(자견용), Vitamine capsule puppy shampoo rinse), (주)크린피스, 애완견과 고양이의 모발보호와 세정작용\\n\\n제품명: 비타민캡슐 삼푸린스(자견용)\\n영문명: Vitamine capsule puppy shampoo rinse)\\n제조업체: (주)크린피스\\n허가일: 2011-05-20\\n성상: 알갱이가 있는 연적색의 점도있는 액상.\\n\\n효능효과: 애완견과 고양이의 모발보호와 세정작용\\n\\n용법용량:\\n가. 적당한 온수로 애견의 피부를 충분히 적셔 주십시\n    오\n나. 충분한 거품과 함께 애견의 전신을 맛사지 하듯 \n    삼푸하십시오\n다. 삼푸후 충분히 헹궈 삼푸기를 완전히 제거해 주십\n    시오\n라. 털이 완전히 마를때까지 충분히 드라이 해 주십시\n    오\\n\\n주의사항: 가. 용도이외에는 사용하지 마십시오\n나. 눈이나 귀에 들어가지 않도록 하시고 만약 들어 \n    갔을 경우 흐르는 물로 닦아 주십시오\n다. 직사광선이 닿는 곳 이나 고온 내지 저온의 장소\n    에 보관하지 마십시오.\n라. 어린이 손에 닿지 않는 곳에 보관하십시오.",
    "metadata": {
      "source_file": "medicine_data_1p~500p.csv",
      "source_type": "csv_medication",
      "batch_number": 13,
      "company": "(주)크린피스",
      "approval_date": "2011-05-20",
      "product_type": "동물용의약외품-제조-095-115",
      "approval_status": "정상",
      "manufacturing_type": "제조",
      "product_name": "비타민캡슐 삼푸린스(자견용)",
      "keywords": [
        "비타민캡슐 삼푸린스(자견용)",
        "Vitamine capsule puppy shampoo rinse)",
        "(주)크린피스",
        "애완견과 고양이의 모발보호와 세정작용"
      ],
      "content_type": "medication_info"
    }
  },
  {
    "id": "med_medicine_data_1p~500p_13_더플러스_탈취제(쟈스민)",
    "text": "문서유형: 동물용의약품 | 제품명: 더플러스 탈취제(쟈스민) | 제조업체: (주)크린피스 | 품목정보: 동물용의약외품-제조-095-116 | 키워드: 더플러스 탈취제(쟈스민), The Plus deodorant(Jasmine), (주)크린피스, 애완동물에 의해 발생되는 악취를 제거해 줍니다.\\n\\n제품명: 더플러스 탈취제(쟈스민)\\n영문명: The Plus deodorant(Jasmine)\\n제조업체: (주)크린피스\\n허가일: 2011-07-22\\n성상: 투명한 무색 액상\\n\\n효능효과: 애완동물에 의해 발생되는 악취를 제거해 줍니다.\\n\\n용법용량:\\n가 .애완동물의 몸에서 악취가 날 때, 몸에 직접 3~4회 분무해 주십시오.\\n\\n주의사항: 가. 사람이나 동물의 눈에 직접 닿지 않게 조심하여  \n    분무하십시오.\n나. 눈에 들어갔을 때에는 즉시 씻을 것\n다. 어린이의 손에 닿지 않는 곳에 보관할 것.\n라. 고온내지 저온의 장소 및 일광이 닿는 곳에는 보\n    관하지 말 것.\n마. 사용후 마개를 닫아 주십시오",
    "metadata": {
      "source_file": "medicine_data_1p~500p.csv",
      "source_type": "csv_medication",
      "batch_number": 13,
      "company": "(주)크린피스",
      "approval_date": "2011-07-22",
      "product_type": "동물용의약외품-제조-095-116",
      "approval_status": "정상",
      "manufacturing_type": "제조",
      "product_name": "더플러스 탈취제(쟈스민)",
      "keywords": [
        "더플러스 탈취제(쟈스민)",
        "The Plus deodorant(Jasmine)",
        "(주)크린피스",
        "애완동물에 의해 발생되는 악취를 제거해 줍니다."
      ],
      "content_type": "medication_info"
    }
  },
  {
    "id": "med_medicine_data_1p~500p_13_더플러스_탈취제(내츄럴)",
    "text": "문서유형: 동물용의약품 | 제품명: 더플러스 탈취제(내츄럴) | 제조업체: (주)크린피스 | 품목정보: 동물용의약외품-제조-095-117 | 키워드: 더플러스 탈취제(내츄럴), The Plus deodorant(Natural), (주)크린피스, 애완동물에 의해 발생되는 악취를 제거해 줍니다.\\n\\n제품명: 더플러스 탈취제(내츄럴)\\n영문명: The Plus deodorant(Natural)\\n제조업체: (주)크린피스\\n허가일: 2011-07-22\\n성상: 투명한 무색 액상\\n\\n효능효과: 애완동물에 의해 발생되는 악취를 제거해 줍니다.\\n\\n용법용량:\\n가. 애완동물의 몸에서 악취가 날 때, 몸에 직접 3~4회 분무해 주십시오.\\n\\n주의사항: 가. 사람이나 동물의 눈에 직접 닿지 않게 조심하여  \n    분무하십시오.\n나. 눈에 들어갔을 때에는 즉시 씻을 것\n다. 어린이의 손에 닿지 않는 곳에 보관할 것.\n라. 고온내지 저온의 장소 및 일광이 닿는 곳에는 보\n    관하지 말 것.\n마. 사용후 마개를 닫아 주십시오",
    "metadata": {
      "source_file": "medicine_data_1p~500p.csv",
      "source_type": "csv_medication",
      "batch_number": 13,
      "company": "(주)크린피스",
      "approval_date": "2011-07-22",
      "product_type": "동물용의약외품-제조-095-117",
      "approval_status": "정상",
      "manufacturing_type": "제조",
      "product_name": "더플러스 탈취제(내츄럴)",
      "keywords": [
        "더플러스 탈취제(내츄럴)",
        "The Plus deodorant(Natural)",
        "(주)크린피스",
        "애완동물에 의해 발생되는 악취를 제거해 줍니다."
      ],
      "content_type": "medication_info"
    }
  },
  {
    "id": "med_medicine_data_1p~500p_13_캐니바쓰마데카쓰삼푸",
    "text": "문서유형: 동물용의약품 | 제품명: 캐니바쓰마데카쓰삼푸 | 제조업체: (주)크린피스 | 품목정보: 동물용의약외품-제조-095-187 | 키워드: 캐니바쓰마데카쓰삼푸, Canibath Madecas shampoo, (주)크린피스, 가. 애완견과 고양이의 비듬과 각질을 감소시켜 주는 삼푸로써 모발\n    보호와 세정작용 및 탈모방지\\n\\n제품명: 캐니바쓰마데카쓰삼푸\\n영문명: Canibath Madecas shampoo\\n제조업체: (주)크린피스\\n허가일: 2016-10-20\\n성상: 연미색 투명한 점도있는 액상\\n\\n효능효과: 가. 애완견과 고양이의 비듬과 각질을 감소시켜 주는 삼푸로써 모발\n    보호와 세정작용 및 탈모방지\\n\\n용법용량:\\n가. 적당한 온수로 애견의 피부를 충분히 적셔 주십시오\n나. 충분한 거품과 함께 애견의 전신을 맛사지 하듯 삼푸하십시오\n다. 삼푸후 충분히 헹궈 삼푸기를 완전히 제거해 주십시오\n라. 털이 완전히 마를때까지 충분히 드라이 해 주십시오\\n\\n주의사항: 가. 용도이외에는 사용하지 마십시오\n나. 눈이나 귀에 들어가지 않도록 하시고 만약 들어 갔을 경우 흐르는 물로 \n    닦아 주십시오\n다. 직사광선이 닿는 곳 이나 고온 내지 저온의 장소에 보관하지 마십시오.\n라. 어린이 손에 닿지 않는 곳에 보관하십시오.",
    "metadata": {
      "source_file": "medicine_data_1p~500p.csv",
      "source_type": "csv_medication",
      "batch_number": 13,
      "company": "(주)크린피스",
      "approval_date": "2016-10-20",
      "product_type": "동물용의약외품-제조-095-187",
      "approval_status": "정상",
      "manufacturing_type": "제조",
      "product_name": "캐니바쓰마데카쓰삼푸",
      "keywords": [
        "캐니바쓰마데카쓰삼푸",
        "Canibath Madecas shampoo",
        "(주)크린피스",
        "가. 애완견과 고양이의 비듬과 각질을 감소시켜 주는 삼푸로써 모발\n    보호와 세정작용 및 탈모방지"
      ],
      "content_type": "medication_info"
    }
  },
  {
    "id": "med_medicine_data_1p~500p_13_캐니바쓰_클록시딘삼푸",
    "text": "문서유형: 동물용의약품 | 제품명: 캐니바쓰 클록시딘삼푸 | 제조업체: (주)크린피스 | 품목정보: 동물용의약외품-제조-095-188 | 키워드: 캐니바쓰 클록시딘삼푸, Canibath Cloxidin shampoo, (주)크린피스, 가. 애완견과 고양이의 비듬과 각질을 감소시켜 주는 삼푸로써 모발\n    보호와 세정작용 및 탈모방지\\n\\n제품명: 캐니바쓰 클록시딘삼푸\\n영문명: Canibath Cloxidin shampoo\\n제조업체: (주)크린피스\\n허가일: 2016-11-10\\n성상: 연미색 투명한 점도있는 액상\\n\\n효능효과: 가. 애완견과 고양이의 비듬과 각질을 감소시켜 주는 삼푸로써 모발\n    보호와 세정작용 및 탈모방지\\n\\n용법용량:\\n가. 적당한 온수로 애견의 피부를 충분히 적셔 주십시오\n나. 충분한 거품과 함께 애견의 전신을 맛사지 하듯 삼푸하십시오\n다. 삼푸후 충분히 헹궈 삼푸기를 완전히 제거해 주십시오\n라. 털이 완전히 마를때까지 충분히 드라이 해 주십시오\\n\\n주의사항: 가. 용도이외에는 사용하지 마십시오\n나. 눈이나 귀에 들어가지 않도록 하시고 만약 들어 갔을 경우 흐르는 물로 \n    닦아 주십시오\n다. 직사광선이 닿는 곳 이나 고온 내지 저온의 장소에 보관하지 마십시오.\n라. 어린이 손에 닿지 않는 곳에 보관하십시오.",
    "metadata": {
      "source_file": "medicine_data_1p~500p.csv",
      "source_type": "csv_medication",
      "batch_number": 13,
      "company": "(주)크린피스",
      "approval_date": "2016-11-10",
      "product_type": "동물용의약외품-제조-095-188",
      "approval_status": "정상",
      "manufacturing_type": "제조",
      "product_name": "캐니바쓰 클록시딘삼푸",
      "keywords": [
        "캐니바쓰 클록시딘삼푸",
        "Canibath Cloxidin shampoo",
        "(주)크린피스",
        "가. 애완견과 고양이의 비듬과 각질을 감소시켜 주는 삼푸로써 모발\n    보호와 세정작용 및 탈모방지"
      ],
      "content_type": "medication_info"
    }
  },
  {
    "id": "med_medicine_data_1p~500p_13_헬로도기_풋_거품_샴푸(푸리메리아향)",
    "text": "문서유형: 동물용의약품 | 제품명: 헬로도기 풋 거품 샴푸(푸리메리아향) | 제조업체: (주)크린피스 | 품목정보: 동물용의약외품-제조-095-189 | 키워드: 헬로도기 풋 거품 샴푸(푸리메리아향), Hellodoggy foot foaming shampoo(Plumeria), (주)크린피스, 가. 애완동물의 피모세정을 위한 삼푸\n나. 피모를 청결하고 건강하게 유지시켜 줍니다.\\n\\n제품명: 헬로도기 풋 거품 샴푸(푸리메리아향)\\n영문명: Hellodoggy foot foaming shampoo(Plumeria)\\n제조업체: (주)크린피스\\n허가일: 2016-11-28\\n성상: 연미색의 액상.\\n\\n효능효과: 가. 애완동물의 피모세정을 위한 삼푸\n나. 피모를 청결하고 건강하게 유지시켜 줍니다.\\n\\n용법용량:\\n가. 삼푸 전에 털을 빗어주어 엉킴을 방지해 줍니다.\n나. 내용물을 삼푸할 부위에 적량을 취하여 털을 마사지하듯 충분히 비벼준다.\n다. 마른수건으로 닦아준 후 드라이로 말리거나 브러쉬를 해준다.\n라. 필요에 따라 반복 실시한다.\n마. 1주 또는 1주 1～2회 간격으로 사용한다.\\n\\n주의사항: 가. 용도이외에는 사용하지 마십시오\n나. 눈이나 귀에 들어가지 않도록 하시고 만약 들어 갔을 경우 흐르는 물로 닦 \n    아 주십시오\n다. 직사광선이 닿는 곳 이나 고온 내지 저온의 장소에 보관하지 마십시오.\n라. 어린이 손에 닿지 않는 곳에 보관하십시오.",
    "metadata": {
      "source_file": "medicine_data_1p~500p.csv",
      "source_type": "csv_medication",
      "batch_number": 13,
      "company": "(주)크린피스",
      "approval_date": "2016-11-28",
      "product_type": "동물용의약외품-제조-095-189",
      "approval_status": "정상",
      "manufacturing_type": "제조",
      "product_name": "헬로도기 풋 거품 샴푸(푸리메리아향)",
      "keywords": [
        "헬로도기 풋 거품 샴푸(푸리메리아향)",
        "Hellodoggy foot foaming shampoo(Plumeria)",
        "(주)크린피스",
        "가. 애완동물의 피모세정을 위한 삼푸\n나. 피모를 청결하고 건강하게 유지시켜 줍니다."
      ],
      "content_type": "medication_info"
    }
  },
  {
    "id": "med_medicine_data_1p~500p_13_헬로도기_풋_거품_샴푸(베이비파우더향)",
    "text": "문서유형: 동물용의약품 | 제품명: 헬로도기 풋 거품 샴푸(베이비파우더향) | 제조업체: (주)크린피스 | 품목정보: 동물용의약외품-제조-095-190 | 키워드: 헬로도기 풋 거품 샴푸(베이비파우더향), Hellodoggy foot foaming shampoo(Baby powder), (주)크린피스, 가. 애완동물의 피모세정을 위한 삼푸\n나. 피모를 청결하고 건강하게 유지시켜 줍니다.\\n\\n제품명: 헬로도기 풋 거품 샴푸(베이비파우더향)\\n영문명: Hellodoggy foot foaming shampoo(Baby powder)\\n제조업체: (주)크린피스\\n허가일: 2016-11-28\\n성상: 연미색의 액상.\\n\\n효능효과: 가. 애완동물의 피모세정을 위한 삼푸\n나. 피모를 청결하고 건강하게 유지시켜 줍니다.\\n\\n용법용량:\\n가. 삼푸 전에 털을 빗어주어 엉킴을 방지해 줍니다.\n나. 내용물을 삼푸할 부위에 적량을 취하여 털을 마사지하듯 충분히 비벼준다.\n다. 마른수건으로 닦아준 후 드라이로 말리거나 브러쉬를 해준다.\n라. 필요에 따라 반복 실시한다.\n마. 1주 또는 1주 1～2회 간격으로 사용한다.\\n\\n주의사항: 가. 용도이외에는 사용하지 마십시오\n나. 눈이나 귀에 들어가지 않도록 하시고 만약 들어 갔을 경우 흐르는 물로 닦 \n    아 주십시오\n다. 직사광선이 닿는 곳 이나 고온 내지 저온의 장소에 보관하지 마십시오.\n라. 어린이 손에 닿지 않는 곳에 보관하십시오.",
    "metadata": {
      "source_file": "medicine_data_1p~500p.csv",
      "source_type": "csv_medication",
      "batch_number": 13,
      "company": "(주)크린피스",
      "approval_date": "2016-11-28",
      "product_type": "동물용의약외품-제조-095-190",
      "approval_status": "정상",
      "manufacturing_type": "제조",
      "product_name": "헬로도기 풋 거품 샴푸(베이비파우더향)",
      "keywords": [
        "헬로도기 풋 거품 샴푸(베이비파우더향)",
        "Hellodoggy foot foaming shampoo(Baby powder)",
        "(주)크린피스",
        "가. 애완동물의 피모세정을 위한 삼푸\n나. 피모를 청결하고 건강하게 유지시켜 줍니다."
      ],
      "content_type": "medication_info"
    }
  },
  {
    "id": "med_medicine_data_1p~500p_13_주문용배합사료첨가제",
    "text": "문서유형: 동물용의약품 | 제품명: 주문용배합사료첨가제 | 제조업체: (주)씨티씨바이오 | 품목정보: 동물용의약품-제조-096-001 | 키워드: 주문용배합사료첨가제, (주)씨티씨바이오, 부족영양성분의 보퉁, 사료효율의 증진을 통한 영양성\n질병의 예방 및 성장촉진\\n\\n제품명: 주문용배합사료첨가제\\n제조업체: (주)씨티씨바이오\\n허가일: 1999-05-31\\n성상: 주문된 각 제제의 성상\\n\\n주요 원료약품:\\n• Abbreviation: 적량\\n\\n효능효과: 부족영양성분의 보퉁, 사료효율의 증진을 통한 영양성\n질병의 예방 및 성장촉진\\n\\n용법용량:\\n배합사료 제조업체의 주문에 의함.\\n\\n주의사항: 1) 배합사료 제조업체의 주문에 의해 생산\n2) 한국동물약품협회에 제조신고를 필한 후 생산,\n   공급\n3) 제조신고된 배합사료 공장 이외에는 판매할 수\n   없음.\n4) 3개 유효성분 이상 혼합되어야 함.\n5) 외부 포장에 주문용사료첨가제, 제조신고번호\n   및 일자, 주문배합사료공장에 한하여 판매라는\n   문구를 삽입하여야 함.\n6) 사용상의 주의사항\n - 사료에 균등하게 혼합하여 사용하십시오.\n - 취급자는 장갑, 마스크, 방독면, 보호의등 보호\n   장구를 착용하여 직접적인 피부접촉이나 흡입을\n   피하여 주십시오.\n - 취...",
    "metadata": {
      "source_file": "medicine_data_1p~500p.csv",
      "source_type": "csv_medication",
      "batch_number": 13,
      "company": "(주)씨티씨바이오",
      "approval_date": "1999-05-31",
      "product_type": "동물용의약품-제조-096-001",
      "approval_status": "정상",
      "manufacturing_type": "제조",
      "product_name": "주문용배합사료첨가제",
      "keywords": [
        "주문용배합사료첨가제",
        "(주)씨티씨바이오",
        "부족영양성분의 보퉁",
        "사료효율의 증진을 통한 영양성\n질병의 예방 및 성장촉진"
      ],
      "content_type": "medication_info"
    }
  },
  {
    "id": "med_medicine_data_1p~500p_13_월드랩스",
    "text": "문서유형: 동물용의약품 | 제품명: 월드랩스 | 제조업체: (주)씨티씨바이오 | 품목정보: 동물용의약품-제조-096-002 | 키워드: 월드랩스, World Labs, (주)씨티씨바이오, - 돼지, 닭 : 사료효율 개선\\n\\n제품명: 월드랩스\\n영문명: World Labs\\n제조업체: (주)씨티씨바이오\\n허가일: 1999-08-24\\n성상: 담갈색 또는 회색의 분말\\n\\n주요 원료약품:\\n• 락토바실러스 카제이(Lactobacillus casei; 10^11 CFU): 100,000.000 MCFU\\n• 바실러스 서브틸리스(Bacillus subtillis; 10^9 CFU): 1,000.000 MCFU\\n• 시카로마이세스 세레비지애(Saccharomyces cerevisiae; 10^8 CFU): 100.000 MCFU\\n• 아스퍼질러스 오리재(Aspergillus oryzaee; 10^8 CFU): 100.000 MCFU\\n• 스트렙토마이세스 그리세우스(Streptomyces griseus; 10^8 CFU): 100.000 MCFU\\n• 부형제(제올라이트, 왕겨, 별규): 적량\\n\\n효능효과: - 돼지, 닭 : 사료효율 개선, 증체율 향상, 성장촉진, 축산환경개선\n- 소 : 사료효율 개선, 증체율 향상, 유량개선, 축산환경개선\\n\\n용법용량:\\n사료 톤당 본제 1kg(0.1%)을 잘 섞어 급여한다.\\n\\n주의사항: - 사용방법상의 주의사항\n 1) 정해진 용법, 용량을 준수하십시오.\n 2) 사료에 균등하게 혼합하여 사용하십시오.\n 3) 취급자는 장갑, 마스크, 방독면, 보호의등 보호장구를 착용하여 \n    직접적인 피부접촉이나 흡입을 피하여 주십시오.\n 4) 취급시 먼지가 나지 않도록 주의하고 작업장소는 \n    충분히 환기시켜 주십시오.\n 5) 사료에 첨가후 가급적 빨리 사용해 주십시오.\n- 기타 주의사항\n 1) 본 제품은 동물용의약품이므로 사람에게 절대 사용하지 마십시오.\n 2) 어린이의 손이 닿지 않고 동물의 접근이 불가능한 곳에 보관하십...",
    "metadata": {
      "source_file": "medicine_data_1p~500p.csv",
      "source_type": "csv_medication",
      "batch_number": 13,
      "company": "(주)씨티씨바이오",
      "approval_date": "1999-08-24",
      "product_type": "동물용의약품-제조-096-002",
      "approval_status": "정상",
      "manufacturing_type": "제조",
      "product_name": "월드랩스",
      "keywords": [
        "월드랩스",
        "World Labs",
        "(주)씨티씨바이오",
        "- 돼지",
        "닭 : 사료효율 개선",
        "증체율 향상",
        "성장촉진",
        "축산환경개선\n- 소 : 사료효율 개선"
      ],
      "content_type": "medication_info"
    }
  },
  {
    "id": "med_medicine_data_1p~500p_13_메치오닌500",
    "text": "문서유형: 동물용의약품 | 제품명: 메치오닌500 | 제조업체: (주)씨티씨바이오 | 품목정보: 동물용의약품-제조-096-005 | 키워드: 메치오닌500, (주)씨티씨바이오, 돼지, 가금에 있어\n1) 성장촉진 및 사료효율 개선\n2) 산란율 증가\n3) 지방간 예방 및 치료\n4) 환우기간 단축\\n\\n제품명: 메치오닌500\\n제조업체: (주)씨티씨바이오\\n허가일: 1999-09-11\\n성상: 특이한 냄새 및 약간 단맛을 띄는 연갈색의 분말\\n\\n주요 원료약품:\\n• DL-Methionine: 500.000 GM\\n• 부형제(탈지강 또는 말분): 적량\\n\\n효능효과: 돼지, 가금에 있어\n1) 성장촉진 및 사료효율 개선\n2) 산란율 증가\n3) 지방간 예방 및 치료\n4) 환우기간 단축\\n\\n용법용량:\\n배합사료에 본제를 아래와 같이 골고루 혼합하여 투여\n한다.\n─────────────────────────\n 대 상 동 물               첨    가    량\n─────────────────────────\n닭    병아리                  0.1 - 0.4%\n      산란계                 0.06 - 0.2%\n      육  계                 0.08 - 0.3%\n--------------------------------------------------\n돼지  자  돈                  0.1 - 0.3%\n      육성돈                 0.06 - 0.2%\n─────────────────────────\\n\\n주의사항: 1) 사용방법상의 주의사항\n - 사료에 균등하게 혼합하여 사용하십시오.\n - 취급시 먼지가 나지 않도록 주의하고 작업장소는\n   환기시켜 주십시오.\n2) 기타주의사항\n - 본 제품은 동물용의약품이므로 사람에게 절대\n   사용하지 마십시오.\n - 어린이의 손이 닿지 않고 동물의 접근이 불가능한\n   곳에 보관하십시오.\n - 유효기간이 경과한 제품은 사용하지 마시고 안전\n   하게 폐기처리 하십시오.\n - 제제의 흡입 또는 불필요한 접촉을 피하고 피부\n   또는 눈에 접촉되었을 경우 흐르는 물에 깨끗이\n   세척하며, 먹었을 경우 구강...",
    "metadata": {
      "source_file": "medicine_data_1p~500p.csv",
      "source_type": "csv_medication",
      "batch_number": 13,
      "company": "(주)씨티씨바이오",
      "approval_date": "1999-09-11",
      "product_type": "동물용의약품-제조-096-005",
      "approval_status": "정상",
      "manufacturing_type": "제조",
      "product_name": "메치오닌500",
      "keywords": [
        "메치오닌500",
        "(주)씨티씨바이오",
        "돼지",
        "가금에 있어\n1) 성장촉진 및 사료효율 개선\n2) 산란율 증가\n3) 지방간 예방 및 치료\n4) 환우기간 단축"
      ],
      "content_type": "medication_info"
    }
  },
  {
    "id": "med_medicine_data_1p~500p_13_더플러스_탈취제(베이비파우더)",
    "text": "문서유형: 동물용의약품 | 제품명: 더플러스 탈취제(베이비파우더) | 제조업체: (주)크린피스 | 품목정보: 동물용의약외품-제조-095-118 | 키워드: 더플러스 탈취제(베이비파우더), The Plus deodorant(Baby Powder), (주)크린피스, 애완동물에 의해 발생되는 악취를 제거해 줍니다.\\n\\n제품명: 더플러스 탈취제(베이비파우더)\\n영문명: The Plus deodorant(Baby Powder)\\n제조업체: (주)크린피스\\n허가일: 2011-07-22\\n성상: 투명한 무색 액상\\n\\n효능효과: 애완동물에 의해 발생되는 악취를 제거해 줍니다.\\n\\n용법용량:\\n가. 애완동물의 몸에서 악취가 날 때, 몸에 직접 3~4회 분무해 주십시오.\\n\\n주의사항: 가. 사람이나 동물의 눈에 직접 닿지 않게 조심하여  \n    분무하십시오.\n나. 눈에 들어갔을 때에는 즉시 씻을 것\n다. 어린이의 손에 닿지 않는 곳에 보관할 것.\n라. 고온내지 저온의 장소 및 일광이 닿는 곳에는 보\n    관하지 말 것.\n마. 사용후 마개를 닫아 주십시오",
    "metadata": {
      "source_file": "medicine_data_1p~500p.csv",
      "source_type": "csv_medication",
      "batch_number": 13,
      "company": "(주)크린피스",
      "approval_date": "2011-07-22",
      "product_type": "동물용의약외품-제조-095-118",
      "approval_status": "정상",
      "manufacturing_type": "제조",
      "product_name": "더플러스 탈취제(베이비파우더)",
      "keywords": [
        "더플러스 탈취제(베이비파우더)",
        "The Plus deodorant(Baby Powder)",
        "(주)크린피스",
        "애완동물에 의해 발생되는 악취를 제거해 줍니다."
      ],
      "content_type": "medication_info"
    }
  },
  {
    "id": "med_medicine_data_1p~500p_13_도기프렌드더플러스치약",
    "text": "문서유형: 동물용의약품 | 제품명: 도기프렌드더플러스치약 | 제조업체: (주)크린피스 | 품목정보: 동물용의약외품-제조-095-119 | 키워드: 도기프렌드더플러스치약, Doggy friend The Plus toothpaste, (주)크린피스, 애견의 구강내 치아 세척 및 프라그제거, 냄새 제거.\\n\\n제품명: 도기프렌드더플러스치약\\n영문명: Doggy friend The Plus toothpaste\\n제조업체: (주)크린피스\\n허가일: 2011-08-30\\n성상: 연녹색의 크림상\\n\\n효능효과: 애견의 구강내 치아 세척 및 프라그제거, 냄새 제거.\\n\\n용법용량:\\n애견의 구강에 묻혀 양치질을 한다.\\n\\n주의사항: 가. 애완동물용이므로 사람에게는 사용하지 말것.\n나. 구강, 치아에 질병이 있는 개와 고양이에게는 수\n    의사와 상담 후 사용할 것.\n다. 사용 후 마개를 닫아둘 것.\n라. 유, 소아의 손에 닿지 않는 곳에 보관할 것.\n마. 고온 내지 저온의 장소 및 일광이 닿는 곳에는 보\n    관하지 말것.",
    "metadata": {
      "source_file": "medicine_data_1p~500p.csv",
      "source_type": "csv_medication",
      "batch_number": 13,
      "company": "(주)크린피스",
      "approval_date": "2011-08-30",
      "product_type": "동물용의약외품-제조-095-119",
      "approval_status": "정상",
      "manufacturing_type": "제조",
      "product_name": "도기프렌드더플러스치약",
      "keywords": [
        "도기프렌드더플러스치약",
        "Doggy friend The Plus toothpaste",
        "(주)크린피스",
        "애견의 구강내 치아 세척 및 프라그제거",
        "냄새 제거."
      ],
      "content_type": "medication_info"
    }
  }
]